inventorize1
