Metadata-Version: 2.1
Name: inventorize1
Version: 0.0.2
Summary: inventory analytics,revenue management and cost calculations for SKUs
Home-page: UNKNOWN
Author: Haytham Omar
Author-email: haytham@rescaleanalytics.com
License: UNKNOWN
Keywords: inventory,pricing
Platform: UNKNOWN
Classifier: Programming Language :: Python :: 3
Classifier: License :: OSI Approved :: MIT License
Classifier: Operating System :: OS Independent
Requires-Python: >=3.6
